{"cameraMode":{"drawMode":0,"name":"Shaded","section":"Shading Mode"},"sceneLighting":true,"audioPlay":false,"sceneViewState":{"showFog":true,"showMaterialUpdate":false,"showSkybox":true,"showFlares":true,"showImageEffects":true,"showParticleSystems":true},"in2DMode":false,"pivot":{"x":765.9093017578125,"y":894.6026611328125,"z":-85.93344116210938},"rotation":{"x":0.26101240515708926,"y":-0.2764889597892761,"z":0.07840947806835175,"w":0.9216331839561462},"size":260.3251037597656,"orthographic":false}